django_lark/__init__.py
django_lark/admin.py
django_lark/apps.py
django_lark/checks.py
django_lark/client.py
django_lark/conf.py
django_lark/decorators.py
django_lark/models.py
django_lark/urls.py
django_lark/utils.py
django_lark/views.py
django_lark/templatetags/__init__.py
django_lark/templatetags/lark_tags.py
django_lark-0.3.0.dist-info/METADATA
django_lark-0.3.0.dist-info/WHEEL
django_lark-0.3.0.dist-info/RECORD
