Metadata-Version: 2.4
Name: django-lark
Version: 0.3.0
Summary: Django integration for Lark billing
Project-URL: Homepage, https://github.com/uselark/django-lark
Project-URL: Documentation, https://github.com/uselark/django-lark#readme
Project-URL: Repository, https://github.com/uselark/django-lark
Project-URL: Issues, https://github.com/uselark/django-lark/issues
Author-email: Lark <support@uselark.ai>
License-Expression: MIT
Classifier: Development Status :: 4 - Beta
Classifier: Environment :: Web Environment
Classifier: Framework :: Django
Classifier: Framework :: Django :: 4.2
Classifier: Framework :: Django :: 5.0
Classifier: Framework :: Django :: 5.1
Classifier: Intended Audience :: Developers
Classifier: License :: OSI Approved :: MIT License
Classifier: Operating System :: OS Independent
Classifier: Programming Language :: Python :: 3
Classifier: Programming Language :: Python :: 3.9
Classifier: Programming Language :: Python :: 3.10
Classifier: Programming Language :: Python :: 3.11
Classifier: Programming Language :: Python :: 3.12
Classifier: Programming Language :: Python :: 3.13
Classifier: Topic :: Internet :: WWW/HTTP
Classifier: Topic :: Software Development :: Libraries :: Python Modules
Requires-Python: >=3.9
Requires-Dist: django>=4.2
Requires-Dist: lark-billing>=0.9.0
Provides-Extra: dev
Requires-Dist: django-stubs>=4.2; extra == 'dev'
Requires-Dist: mypy>=1.0; extra == 'dev'
Requires-Dist: pytest-asyncio>=0.21; extra == 'dev'
Requires-Dist: pytest-django>=4.5; extra == 'dev'
Requires-Dist: pytest>=7.0; extra == 'dev'
